{
  "project_info": {
    "project_number": "259337742082",
    "project_id": "firebase-freekick"
  },
  "client": [
    {
      "client_info": {
        "mobilesdk_app_id": "1:259337742082:android:63d65da6a3ee1b04",
        "android_client_info": {
          "package_name": "com.football.freekick"
        }
      },
      "oauth_client": [
        {
          "client_id": "259337742082-ea9bgavjb9s751akcbet8i2benqngio8.apps.googleusercontent.com",
          "client_type": 3
        }
      ],
      "api_key": [
        {
          "current_key": "AIzaSyBZ8eyCUj0IBLj6GDGD6iVvPOwbtJEDN9Q"
        }
      ],
      "services": {
        "analytics_service": {
          "status": 1
        },
        "appinvite_service": {
          "status": 1,
          "other_platform_oauth_client": []
        },
        "ads_service": {
          "status": 1
        }
      }
    }
  ],
  "configuration_version": "1"
}